Workbook

Sheet Sales Data
A1: Date | B1: Month | C1: Region | D1: Sales Rep | E1: Product | F1: Category | G1: Units Sold | H1: Unit Price | I1: Revenue | J1: COGS | K1: Gross Profit | L1: Margin %
A2: 45619 | B2: Nov | C2: South | D2: Bob Ochieng | E2: Wireless Mouse | F2: Peripherals | G2: 2 | H2: 31.1 | I2: =G2*H2 -> 62.2 | J2: =I2*0.499 -> 31.0378 | K2: =I2-J2 -> 31.1622 | L2: =IF(I2=0,0,K2/I2) -> 0.501
A3: 45638 | B3: Dec | C3: South | D3: David Kamau | E3: Wireless Mouse | F3: Peripherals | G3: 38 | H3: 28.32 | I3: =G3*H3 -> 1076.16 | J3: =I3*0.456 -> 490.72896 | K3: =I3-J3 -> 585.43104 | L3: =IF(I3=0,0,K3/I3) -> 0.544
A4: 45550 | B4: Sep | C4: Central | D4: Grace Akinyi | E4: Laptop Pro | F4: Computers | G4: 36 | H4: 1181.64 | I4: =G4*H4 -> 42539.04 | J4: =I4*0.58 -> 24672.643 | K4: =I4-J4 -> 17866.397 | L4: =IF(I4=0,0,K4/I4) -> 0.42
A5: 45404 | B5: Apr | C5: South | D5: Grace Akinyi | E5: Ergonomic Chair | F5: Furniture | G5: 38 | H5: 419.12 | I5: =G5*H5 -> 15926.56 | J5: =I5*0.624 -> 9938.1734 | K5: =I5-J5 -> 5988.3866 | L5: =IF(I5=0,0,K5/I5) -> 0.376
A6: 45466 | B6: Jun | C6: North | D6: Bob Ochieng | E6: USB-C Hub | F6: Accessories | G6: 10 | H6: 41.16 | I6: =G6*H6 -> 411.6 | J6: =I6*0.603 -> 248.1948 | K6: =I6-J6 -> 163.4052 | L6: =IF(I6=0,0,K6/I6) -> 0.397
A7: 45486 | B7: Jul | C7: North | D7: Henry Mwenda | E7: Wireless Mouse | F7: Peripherals | G7: 23 | H7: 32.02 | I7: =G7*H7 -> 736.46 | J7: =I7*0.571 -> 420.51866 | K7: =I7-J7 -> 315.94134 | L7: =IF(I7=0,0,K7/I7) -> 0.429
A8: 45566 | B8: Oct | C8: Central | D8: Frank Otieno | E8: Wireless Mouse | F8: Peripherals | G8: 25 | H8: 25.34 | I8: =G8*H8 -> 633.5 | J8: =I8*0.509 -> 322.4515 | K8: =I8-J8 -> 311.0485 | L8: =IF(I8=0,0,K8/I8) -> 0.491
A9: 45587 | B9: Oct | C9: East | D9: Bob Ochieng | E9: Mechanical Keyboard | F9: Peripherals | G9: 46 | H9: 77.51 | I9: =G9*H9 -> 3565.46 | J9: =I9*0.582 -> 2075.0977 | K9: =I9-J9 -> 1490.3623 | L9: =IF(I9=0,0,K9/I9) -> 0.418
A10: 45411 | B10: Apr | C10: East | D10: Carol Njeri | E10: Wireless Mouse | F10: Peripherals | G10: 25 | H10: 27.07 | I10: =G10*H10 -> 676.75 | J10: =I10*0.577 -> 390.48475 | K10: =I10-J10 -> 286.26525 | L10: =IF(I10=0,0,K10/I10) -> 0.423
A11: 45481 | B11: Jul | C11: North | D11: Carol Njeri | E11: Webcam HD | F11: Accessories | G11: 14 | H11: 135.59 | I11: =G11*H11 -> 1898.26 | J11: =I11*0.59 -> 1119.9734 | K11: =I11-J11 -> 778.2866 | L11: =IF(I11=0,0,K11/I11) -> 0.41
A12: 45565 | B12: Sep | C12: Central | D12: David Kamau | E12: Mechanical Keyboard | F12: Peripherals | G12: 11 | H12: 87.99 | I12: =G12*H12 -> 967.89 | J12: =I12*0.504 -> 487.81656 | K12: =I12-J12 -> 480.07344 | L12: =IF(I12=0,0,K12/I12) -> 0.496
A13: 45642 | B13: Dec | C13: North | D13: Frank Otieno | E13: Webcam HD | F13: Accessories | G13: 50 | H13: 139.68 | I13: =G13*H13 -> 6984 | J13: =I13*0.496 -> 3464.064 | K13: =I13-J13 -> 3519.936 | L13: =IF(I13=0,0,K13/I13) -> 0.504
A14: 45497 | B14: Jul | C14: East | D14: David Kamau | E14: USB-C Hub | F14: Accessories | G14: 5 | H14: 41.1 | I14: =G14*H14 -> 205.5 | J14: =I14*0.639 -> 131.3145 | K14: =I14-J14 -> 74.1855 | L14: =IF(I14=0,0,K14/I14) -> 0.361
A15: 45627 | B15: Dec | C15: South | D15: Eve Wanjiku | E15: Ergonomic Chair | F15: Furniture | G15: 26 | H15: 500.82 | I15: =G15*H15 -> 13021.32 | J15: =I15*0.579 -> 7539.3443 | K15: =I15-J15 -> 5481.9757 | L15: =IF(I15=0,0,K15/I15) -> 0.421
A16: 45363 | B16: Mar | C16: Central | D16: Grace Akinyi | E16: Mechanical Keyboard | F16: Peripherals | G16: 48 | H16: 90.64 | I16: =G16*H16 -> 4350.72 | J16: =I16*0.503 -> 2188.4122 | K16: =I16-J16 -> 2162.3078 | L16: =IF(I16=0,0,K16/I16) -> 0.497
A17: 45590 | B17: Oct | C17: Central | D17: Henry Mwenda | E17: Standing Desk | F17: Furniture | G17: 24 | H17: 365.4 | I17: =G17*H17 -> 8769.6 | J17: =I17*0.65 -> 5700.24 | K17: =I17-J17 -> 3069.36 | L17: =IF(I17=0,0,K17/I17) -> 0.35
A18: 45338 | B18: Feb | C18: West | D18: Bob Ochieng | E18: Laptop Pro | F18: Computers | G18: 8 | H18: 1163.71 | I18: =G18*H18 -> 9309.68 | J18: =I18*0.482 -> 4487.2658 | K18: =I18-J18 -> 4822.4142 | L18: =IF(I18=0,0,K18/I18) -> 0.518
A19: 45489 | B19: Jul | C19: Central | D19: Alice Mwangi | E19: Standing Desk | F19: Furniture | G19: 39 | H19: 458.39 | I19: =G19*H19 -> 17877.21 | J19: =I19*0.556 -> 9939.7288 | K19: =I19-J19 -> 7937.4812 | L19: =IF(I19=0,0,K19/I19) -> 0.444
A20: 45640 | B20: Dec | C20: East | D20: Bob Ochieng | E20: Wireless Mouse | F20: Peripherals | G20: 44 | H20: 32.35 | I20: =G20*H20 -> 1423.4 | J20: =I20*0.6 -> 854.04 | K20: =I20-J20 -> 569.36 | L20: =IF(I20=0,0,K20/I20) -> 0.4
A21: 45442 | B21: May | C21: East | D21: Carol Njeri | E21: Standing Desk | F21: Furniture | G21: 11 | H21: 393.46 | I21: =G21*H21 -> 4328.06 | J21: =I21*0.641 -> 2774.2865 | K21: =I21-J21 -> 1553.7735 | L21: =IF(I21=0,0,K21/I21) -> 0.359
A22: 45551 | B22: Sep | C22: Central | D22: David Kamau | E22: Wireless Mouse | F22: Peripherals | G22: 41 | H22: 27.25 | I22: =G22*H22 -> 1117.25 | J22: =I22*0.578 -> 645.7705 | K22: =I22-J22 -> 471.4795 | L22: =IF(I22=0,0,K22/I22) -> 0.422
A23: 45370 | B23: Mar | C23: Central | D23: Alice Mwangi | E23: Webcam HD | F23: Accessories | G23: 49 | H23: 115.9 | I23: =G23*H23 -> 5679.1 | J23: =I23*0.641 -> 3640.3031 | K23: =I23-J23 -> 2038.7969 | L23: =IF(I23=0,0,K23/I23) -> 0.359
A24: 45598 | B24: Nov | C24: East | D24: David Kamau | E24: Webcam HD | F24: Accessories | G24: 32 | H24: 110.4 | I24: =G24*H24 -> 3532.8 | J24: =I24*0.636 -> 2246.8608 | K24: =I24-J24 -> 1285.9392 | L24: =IF(I24=0,0,K24/I24) -> 0.364
A25: 45321 | B25: Jan | C25: West | D25: Bob Ochieng | E25: Mechanical Keyboard | F25: Peripherals | G25: 37 | H25: 100.93 | I25: =G25*H25 -> 3734.41 | J25: =I25*0.467 -> 1743.9695 | K25: =I25-J25 -> 1990.4405 | L25: =IF(I25=0,0,K25/I25) -> 0.533
A26: 45564 | B26: Sep | C26: South | D26: Eve Wanjiku | E26: 4K Monitor | F26: Displays | G26: 9 | H26: 627.71 | I26: =G26*H26 -> 5649.39 | J26: =I26*0.639 -> 3609.9602 | K26: =I26-J26 -> 2039.4298 | L26: =IF(I26=0,0,K26/I26) -> 0.361
A27: 45562 | B27: Sep | C27: South | D27: Eve Wanjiku | E27: Standing Desk | F27: Furniture | G27: 14 | H27: 450.34 | I27: =G27*H27 -> 6304.76 | J27: =I27*0.601 -> 3789.1608 | K27: =I27-J27 -> 2515.5992 | L27: =IF(I27=0,0,K27/I27) -> 0.399
A28: 45496 | B28: Jul | C28: South | D28: David Kamau | E28: Webcam HD | F28: Accessories | G28: 29 | H28: 144.47 | I28: =G28*H28 -> 4189.63 | J28: =I28*0.54 -> 2262.4002 | K28: =I28-J28 -> 1927.2298 | L28: =IF(I28=0,0,K28/I28) -> 0.46
A29: 45324 | B29: Feb | C29: South | D29: Alice Mwangi | E29: Webcam HD | F29: Accessories | G29: 2 | H29: 132.42 | I29: =G29*H29 -> 264.84 | J29: =I29*0.496 -> 131.36064 | K29: =I29-J29 -> 133.47936 | L29: =IF(I29=0,0,K29/I29) -> 0.504
A30: 45328 | B30: Feb | C30: East | D30: Bob Ochieng | E30: Laptop Pro | F30: Computers | G30: 15 | H30: 1130.42 | I30: =G30*H30 -> 16956.3 | J30: =I30*0.456 -> 7732.0728 | K30: =I30-J30 -> 9224.2272 | L30: =IF(I30=0,0,K30/I30) -> 0.544
A31: 45555 | B31: Sep | C31: South | D31: Henry Mwenda | E31: Mechanical Keyboard | F31: Peripherals | G31: 18 | H31: 93.51 | I31: =G31*H31 -> 1683.18 | J31: =I31*0.493 -> 829.80774 | K31: =I31-J31 -> 853.37226 | L31: =IF(I31=0,0,K31/I31) -> 0.507
A32: 45416 | B32: May | C32: West | D32: Frank Otieno | E32: Ergonomic Chair | F32: Furniture | G32: 27 | H32: 407.3 | I32: =G32*H32 -> 10997.1 | J32: =I32*0.469 -> 5157.6399 | K32: =I32-J32 -> 5839.4601 | L32: =IF(I32=0,0,K32/I32) -> 0.531
A33: 45508 | B33: Aug | C33: North | D33: Alice Mwangi | E33: Standing Desk | F33: Furniture | G33: 30 | H33: 442.55 | I33: =G33*H33 -> 13276.5 | J33: =I33*0.461 -> 6120.4665 | K33: =I33-J33 -> 7156.0335 | L33: =IF(I33=0,0,K33/I33) -> 0.539
A34: 45498 | B34: Jul | C34: West | D34: Carol Njeri | E34: Webcam HD | F34: Accessories | G34: 7 | H34: 119.27 | I34: =G34*H34 -> 834.89 | J34: =I34*0.488 -> 407.42632 | K34: =I34-J34 -> 427.46368 | L34: =IF(I34=0,0,K34/I34) -> 0.512
A35: 45508 | B35: Aug | C35: North | D35: Henry Mwenda | E35: 4K Monitor | F35: Displays | G35: 18 | H35: 592.28 | I35: =G35*H35 -> 10661.04 | J35: =I35*0.625 -> 6663.15 | K35: =I35-J35 -> 3997.89 | L35: =IF(I35=0,0,K35/I35) -> 0.375
A36: 45573 | B36: Oct | C36: North | D36: Bob Ochieng | E36: Wireless Mouse | F36: Peripherals | G36: 4 | H36: 30.32 | I36: =G36*H36 -> 121.28 | J36: =I36*0.558 -> 67.67424 | K36: =I36-J36 -> 53.60576 | L36: =IF(I36=0,0,K36/I36) -> 0.442
A37: 45413 | B37: May | C37: West | D37: Alice Mwangi | E37: 4K Monitor | F37: Displays | G37: 27 | H37: 596.42 | I37: =G37*H37 -> 16103.34 | J37: =I37*0.493 -> 7938.9466 | K37: =I37-J37 -> 8164.3934 | L37: =IF(I37=0,0,K37/I37) -> 0.507
A38: 45376 | B38: Mar | C38: West | D38: Eve Wanjiku | E38: Standing Desk | F38: Furniture | G38: 1 | H38: 457.09 | I38: =G38*H38 -> 457.09 | J38: =I38*0.503 -> 229.91627 | K38: =I38-J38 -> 227.17373 | L38: =IF(I38=0,0,K38/I38) -> 0.497
A39: 45508 | B39: Aug | C39: North | D39: Alice Mwangi | E39: Ergonomic Chair | F39: Furniture | G39: 10 | H39: 407.23 | I39: =G39*H39 -> 4072.3 | J39: =I39*0.494 -> 2011.7162 | K39: =I39-J39 -> 2060.5838 | L39: =IF(I39=0,0,K39/I39) -> 0.506
A40: 45452 | B40: Jun | C40: Central | D40: Carol Njeri | E40: Laptop Pro | F40: Computers | G40: 4 | H40: 1331.8 | I40: =G40*H40 -> 5327.2 | J40: =I40*0.551 -> 2935.2872 | K40: =I40-J40 -> 2391.9128 | L40: =IF(I40=0,0,K40/I40) -> 0.449
A41: 45321 | B41: Jan | C41: South | D41: Grace Akinyi | E41: Wireless Mouse | F41: Peripherals | G41: 12 | H41: 25.25 | I41: =G41*H41 -> 303 | J41: =I41*0.464 -> 140.592 | K41: =I41-J41 -> 162.408 | L41: =IF(I41=0,0,K41/I41) -> 0.536
A42: 45353 | B42: Mar | C42: West | D42: Frank Otieno | E42: Mechanical Keyboard | F42: Peripherals | G42: 38 | H42: 91.52 | I42: =G42*H42 -> 3477.76 | J42: =I42*0.574 -> 1996.2342 | K42: =I42-J42 -> 1481.5258 | L42: =IF(I42=0,0,K42/I42) -> 0.426
A43: 45425 | B43: May | C43: West | D43: Carol Njeri | E43: Mechanical Keyboard | F43: Peripherals | G43: 43 | H43: 94.77 | I43: =G43*H43 -> 4075.11 | J43: =I43*0.498 -> 2029.4048 | K43: =I43-J43 -> 2045.7052 | L43: =IF(I43=0,0,K43/I43) -> 0.502
A44: 45635 | B44: Dec | C44: North | D44: Alice Mwangi | E44: USB-C Hub | F44: Accessories | G44: 30 | H44: 42.52 | I44: =G44*H44 -> 1275.6 | J44: =I44*0.6 -> 765.36 | K44: =I44-J44 -> 510.24 | L44: =IF(I44=0,0,K44/I44) -> 0.4
A45: 45526 | B45: Aug | C45: South | D45: Frank Otieno | E45: Wireless Mouse | F45: Peripherals | G45: 5 | H45: 29.33 | I45: =G45*H45 -> 146.65 | J45: =I45*0.551 -> 80.80415 | K45: =I45-J45 -> 65.84585 | L45: =IF(I45=0,0,K45/I45) -> 0.449
A46: 45327 | B46: Feb | C46: Central | D46: Eve Wanjiku | E46: Mechanical Keyboard | F46: Peripherals | G46: 24 | H46: 83.26 | I46: =G46*H46 -> 1998.24 | J46: =I46*0.538 -> 1075.0531 | K46: =I46-J46 -> 923.18688 | L46: =IF(I46=0,0,K46/I46) -> 0.462
A47: 45605 | B47: Nov | C47: North | D47: Carol Njeri | E47: Laptop Pro | F47: Computers | G47: 43 | H47: 1422.58 | I47: =G47*H47 -> 61170.94 | J47: =I47*0.51 -> 31197.179 | K47: =I47-J47 -> 29973.761 | L47: =IF(I47=0,0,K47/I47) -> 0.49
A48: 45427 | B48: May | C48: East | D48: David Kamau | E48: Wireless Mouse | F48: Peripherals | G48: 7 | H48: 31.11 | I48: =G48*H48 -> 217.77 | J48: =I48*0.481 -> 104.74737 | K48: =I48-J48 -> 113.02263 | L48: =IF(I48=0,0,K48/I48) -> 0.519
A49: 45467 | B49: Jun | C49: West | D49: Eve Wanjiku | E49: Mechanical Keyboard | F49: Peripherals | G49: 44 | H49: 92.58 | I49: =G49*H49 -> 4073.52 | J49: =I49*0.503 -> 2048.9806 | K49: =I49-J49 -> 2024.5394 | L49: =IF(I49=0,0,K49/I49) -> 0.497
A50: 45318 | B50: Jan | C50: North | D50: Frank Otieno | E50: Wireless Mouse | F50: Peripherals | G50: 41 | H50: 28.34 | I50: =G50*H50 -> 1161.94 | J50: =I50*0.505 -> 586.7797 | K50: =I50-J50 -> 575.1603 | L50: =IF(I50=0,0,K50/I50) -> 0.495
A51: 45358 | B51: Mar | C51: West | D51: Alice Mwangi | E51: USB-C Hub | F51: Accessories | G51: 11 | H51: 48.26 | I51: =G51*H51 -> 530.86 | J51: =I51*0.56 -> 297.2816 | K51: =I51-J51 -> 233.5784 | L51: =IF(I51=0,0,K51/I51) -> 0.44
A52: 45349 | B52: Feb | C52: East | D52: Carol Njeri | E52: Wireless Mouse | F52: Peripherals | G52: 45 | H52: 32.51 | I52: =G52*H52 -> 1462.95 | J52: =I52*0.559 -> 817.78905 | K52: =I52-J52 -> 645.16095 | L52: =IF(I52=0,0,K52/I52) -> 0.441
A53: 45512 | B53: Aug | C53: North | D53: Frank Otieno | E53: 4K Monitor | F53: Displays | G53: 3 | H53: 564.54 | I53: =G53*H53 -> 1693.62 | J53: =I53*0.63 -> 1066.9806 | K53: =I53-J53 -> 626.6394 | L53: =IF(I53=0,0,K53/I53) -> 0.37
A54: 45399 | B54: Apr | C54: West | D54: Carol Njeri | E54: Mechanical Keyboard | F54: Peripherals | G54: 43 | H54: 78.39 | I54: =G54*H54 -> 3370.77 | J54: =I54*0.606 -> 2042.6866 | K54: =I54-J54 -> 1328.0834 | L54: =IF(I54=0,0,K54/I54) -> 0.394
A55: 45413 | B55: May | C55: East | D55: Grace Akinyi | E55: 4K Monitor | F55: Displays | G55: 12 | H55: 667.54 | I55: =G55*H55 -> 8010.48 | J55: =I55*0.455 -> 3644.7684 | K55: =I55-J55 -> 4365.7116 | L55: =IF(I55=0,0,K55/I55) -> 0.545
A56: 45634 | B56: Dec | C56: West | D56: Alice Mwangi | E56: Mechanical Keyboard | F56: Peripherals | G56: 18 | H56: 79.9 | I56: =G56*H56 -> 1438.2 | J56: =I56*0.59 -> 848.538 | K56: =I56-J56 -> 589.662 | L56: =IF(I56=0,0,K56/I56) -> 0.41
A57: 45532 | B57: Aug | C57: East | D57: David Kamau | E57: Mechanical Keyboard | F57: Peripherals | G57: 13 | H57: 97.45 | I57: =G57*H57 -> 1266.85 | J57: =I57*0.542 -> 686.6327 | K57: =I57-J57 -> 580.2173 | L57: =IF(I57=0,0,K57/I57) -> 0.458
A58: 45406 | B58: Apr | C58: North | D58: Eve Wanjiku | E58: Laptop Pro | F58: Computers | G58: 43 | H58: 1179.41 | I58: =G58*H58 -> 50714.63 | J58: =I58*0.516 -> 26168.749 | K58: =I58-J58 -> 24545.881 | L58: =IF(I58=0,0,K58/I58) -> 0.484
A59: 45471 | B59: Jun | C59: North | D59: Bob Ochieng | E59: Standing Desk | F59: Furniture | G59: 44 | H59: 456.59 | I59: =G59*H59 -> 20089.96 | J59: =I59*0.557 -> 11190.108 | K59: =I59-J59 -> 8899.8523 | L59: =IF(I59=0,0,K59/I59) -> 0.443
A60: 45425 | B60: May | C60: North | D60: Grace Akinyi | E60: 4K Monitor | F60: Displays | G60: 38 | H60: 682.12 | I60: =G60*H60 -> 25920.56 | J60: =I60*0.503 -> 13038.042 | K60: =I60-J60 -> 12882.518 | L60: =IF(I60=0,0,K60/I60) -> 0.497
A61: 45468 | B61: Jun | C61: West | D61: David Kamau | E61: Webcam HD | F61: Accessories | G61: 28 | H61: 133.11 | I61: =G61*H61 -> 3727.08 | J61: =I61*0.552 -> 2057.3482 | K61: =I61-J61 -> 1669.7318 | L61: =IF(I61=0,0,K61/I61) -> 0.448
A62: 45422 | B62: May | C62: Central | D62: David Kamau | E62: Laptop Pro | F62: Computers | G62: 46 | H62: 1274.08 | I62: =G62*H62 -> 58607.68 | J62: =I62*0.554 -> 32468.655 | K62: =I62-J62 -> 26139.025 | L62: =IF(I62=0,0,K62/I62) -> 0.446
A63: 45478 | B63: Jul | C63: Central | D63: Frank Otieno | E63: Standing Desk | F63: Furniture | G63: 5 | H63: 452.73 | I63: =G63*H63 -> 2263.65 | J63: =I63*0.634 -> 1435.1541 | K63: =I63-J63 -> 828.4959 | L63: =IF(I63=0,0,K63/I63) -> 0.366
A64: 45631 | B64: Dec | C64: West | D64: Frank Otieno | E64: Wireless Mouse | F64: Peripherals | G64: 47 | H64: 32.48 | I64: =G64*H64 -> 1526.56 | J64: =I64*0.551 -> 841.13456 | K64: =I64-J64 -> 685.42544 | L64: =IF(I64=0,0,K64/I64) -> 0.449
A65: 45498 | B65: Jul | C65: West | D65: Carol Njeri | E65: USB-C Hub | F65: Accessories | G65: 36 | H65: 39.97 | I65: =G65*H65 -> 1438.92 | J65: =I65*0.534 -> 768.38328 | K65: =I65-J65 -> 670.53672 | L65: =IF(I65=0,0,K65/I65) -> 0.466
A66: 45607 | B66: Nov | C66: East | D66: David Kamau | E66: USB-C Hub | F66: Accessories | G66: 26 | H66: 45.65 | I66: =G66*H66 -> 1186.9 | J66: =I66*0.45 -> 534.105 | K66: =I66-J66 -> 652.795 | L66: =IF(I66=0,0,K66/I66) -> 0.55
A67: 45512 | B67: Aug | C67: Central | D67: Henry Mwenda | E67: Webcam HD | F67: Accessories | G67: 30 | H67: 126.75 | I67: =G67*H67 -> 3802.5 | J67: =I67*0.585 -> 2224.4625 | K67: =I67-J67 -> 1578.0375 | L67: =IF(I67=0,0,K67/I67) -> 0.415
A68: 45378 | B68: Mar | C68: East | D68: Bob Ochieng | E68: Wireless Mouse | F68: Peripherals | G68: 19 | H68: 29.13 | I68: =G68*H68 -> 553.47 | J68: =I68*0.577 -> 319.35219 | K68: =I68-J68 -> 234.11781 | L68: =IF(I68=0,0,K68/I68) -> 0.423
A69: 45412 | B69: Apr | C69: North | D69: David Kamau | E69: USB-C Hub | F69: Accessories | G69: 15 | H69: 49.14 | I69: =G69*H69 -> 737.1 | J69: =I69*0.479 -> 353.0709 | K69: =I69-J69 -> 384.0291 | L69: =IF(I69=0,0,K69/I69) -> 0.521
A70: 45535 | B70: Aug | C70: South | D70: Grace Akinyi | E70: Wireless Mouse | F70: Peripherals | G70: 30 | H70: 28.26 | I70: =G70*H70 -> 847.8 | J70: =I70*0.576 -> 488.3328 | K70: =I70-J70 -> 359.4672 | L70: =IF(I70=0,0,K70/I70) -> 0.424
A71: 45545 | B71: Sep | C71: North | D71: Grace Akinyi | E71: Standing Desk | F71: Furniture | G71: 16 | H71: 356.81 | I71: =G71*H71 -> 5708.96 | J71: =I71*0.588 -> 3356.8685 | K71: =I71-J71 -> 2352.0915 | L71: =IF(I71=0,0,K71/I71) -> 0.412
A72: 45404 | B72: Apr | C72: South | D72: Bob Ochieng | E72: 4K Monitor | F72: Displays | G72: 45 | H72: 602.23 | I72: =G72*H72 -> 27100.35 | J72: =I72*0.46 -> 12466.161 | K72: =I72-J72 -> 14634.189 | L72: =IF(I72=0,0,K72/I72) -> 0.54
A73: 45525 | B73: Aug | C73: Central | D73: Frank Otieno | E73: 4K Monitor | F73: Displays | G73: 30 | H73: 629.11 | I73: =G73*H73 -> 18873.3 | J73: =I73*0.648 -> 12229.898 | K73: =I73-J73 -> 6643.4016 | L73: =IF(I73=0,0,K73/I73) -> 0.352
A74: 45518 | B74: Aug | C74: West | D74: Henry Mwenda | E74: Standing Desk | F74: Furniture | G74: 36 | H74: 392.53 | I74: =G74*H74 -> 14131.08 | J74: =I74*0.482 -> 6811.1806 | K74: =I74-J74 -> 7319.8994 | L74: =IF(I74=0,0,K74/I74) -> 0.518
A75: 45424 | B75: May | C75: West | D75: David Kamau | E75: Mechanical Keyboard | F75: Peripherals | G75: 41 | H75: 83.05 | I75: =G75*H75 -> 3405.05 | J75: =I75*0.606 -> 2063.4603 | K75: =I75-J75 -> 1341.5897 | L75: =IF(I75=0,0,K75/I75) -> 0.394
A76: 45432 | B76: May | C76: East | D76: Frank Otieno | E76: Ergonomic Chair | F76: Furniture | G76: 5 | H76: 477.76 | I76: =G76*H76 -> 2388.8 | J76: =I76*0.497 -> 1187.2336 | K76: =I76-J76 -> 1201.5664 | L76: =IF(I76=0,0,K76/I76) -> 0.503
A77: 45568 | B77: Oct | C77: South | D77: David Kamau | E77: Wireless Mouse | F77: Peripherals | G77: 9 | H77: 25.96 | I77: =G77*H77 -> 233.64 | J77: =I77*0.527 -> 123.12828 | K77: =I77-J77 -> 110.51172 | L77: =IF(I77=0,0,K77/I77) -> 0.473
A78: 45324 | B78: Feb | C78: North | D78: David Kamau | E78: Standing Desk | F78: Furniture | G78: 27 | H78: 378.76 | I78: =G78*H78 -> 10226.52 | J78: =I78*0.543 -> 5553.0004 | K78: =I78-J78 -> 4673.5196 | L78: =IF(I78=0,0,K78/I78) -> 0.457
A79: 45507 | B79: Aug | C79: Central | D79: Grace Akinyi | E79: Standing Desk | F79: Furniture | G79: 50 | H79: 409.06 | I79: =G79*H79 -> 20453 | J79: =I79*0.589 -> 12046.817 | K79: =I79-J79 -> 8406.183 | L79: =IF(I79=0,0,K79/I79) -> 0.411
A80: 45536 | B80: Sep | C80: West | D80: David Kamau | E80: Laptop Pro | F80: Computers | G80: 23 | H80: 1220.52 | I80: =G80*H80 -> 28071.96 | J80: =I80*0.528 -> 14821.995 | K80: =I80-J80 -> 13249.965 | L80: =IF(I80=0,0,K80/I80) -> 0.472
A81: 45541 | B81: Sep | C81: East | D81: Grace Akinyi | E81: Mechanical Keyboard | F81: Peripherals | G81: 18 | H81: 87.29 | I81: =G81*H81 -> 1571.22 | J81: =I81*0.456 -> 716.47632 | K81: =I81-J81 -> 854.74368 | L81: =IF(I81=0,0,K81/I81) -> 0.544
A82: 45376 | B82: Mar | C82: West | D82: Alice Mwangi | E82: Ergonomic Chair | F82: Furniture | G82: 9 | H82: 513.75 | I82: =G82*H82 -> 4623.75 | J82: =I82*0.557 -> 2575.4288 | K82: =I82-J82 -> 2048.3212 | L82: =IF(I82=0,0,K82/I82) -> 0.443
A83: 45334 | B83: Feb | C83: East | D83: Grace Akinyi | E83: Standing Desk | F83: Furniture | G83: 9 | H83: 442.91 | I83: =G83*H83 -> 3986.19 | J83: =I83*0.486 -> 1937.2883 | K83: =I83-J83 -> 2048.9017 | L83: =IF(I83=0,0,K83/I83) -> 0.514
A84: 45459 | B84: Jun | C84: West | D84: Eve Wanjiku | E84: Mechanical Keyboard | F84: Peripherals | G84: 30 | H84: 84.38 | I84: =G84*H84 -> 2531.4 | J84: =I84*0.602 -> 1523.9028 | K84: =I84-J84 -> 1007.4972 | L84: =IF(I84=0,0,K84/I84) -> 0.398
A85: 45507 | B85: Aug | C85: North | D85: Frank Otieno | E85: USB-C Hub | F85: Accessories | G85: 6 | H85: 44.6 | I85: =G85*H85 -> 267.6 | J85: =I85*0.6 -> 160.56 | K85: =I85-J85 -> 107.04 | L85: =IF(I85=0,0,K85/I85) -> 0.4
A86: 45406 | B86: Apr | C86: North | D86: David Kamau | E86: Wireless Mouse | F86: Peripherals | G86: 50 | H86: 32.98 | I86: =G86*H86 -> 1649 | J86: =I86*0.458 -> 755.242 | K86: =I86-J86 -> 893.758 | L86: =IF(I86=0,0,K86/I86) -> 0.542
A87: 45394 | B87: Apr | C87: North | D87: David Kamau | E87: Laptop Pro | F87: Computers | G87: 40 | H87: 1163.53 | I87: =G87*H87 -> 46541.2 | J87: =I87*0.475 -> 22107.07 | K87: =I87-J87 -> 24434.13 | L87: =IF(I87=0,0,K87/I87) -> 0.525
A88: 45530 | B88: Aug | C88: North | D88: Carol Njeri | E88: USB-C Hub | F88: Accessories | G88: 50 | H88: 43.23 | I88: =G88*H88 -> 2161.5 | J88: =I88*0.571 -> 1234.2165 | K88: =I88-J88 -> 927.2835 | L88: =IF(I88=0,0,K88/I88) -> 0.429
A89: 45451 | B89: Jun | C89: West | D89: Grace Akinyi | E89: Wireless Mouse | F89: Peripherals | G89: 38 | H89: 24.87 | I89: =G89*H89 -> 945.06 | J89: =I89*0.512 -> 483.87072 | K89: =I89-J89 -> 461.18928 | L89: =IF(I89=0,0,K89/I89) -> 0.488
A90: 45393 | B90: Apr | C90: North | D90: Eve Wanjiku | E90: Wireless Mouse | F90: Peripherals | G90: 38 | H90: 30.66 | I90: =G90*H90 -> 1165.08 | J90: =I90*0.575 -> 669.921 | K90: =I90-J90 -> 495.159 | L90: =IF(I90=0,0,K90/I90) -> 0.425
A91: 45642 | B91: Dec | C91: West | D91: Frank Otieno | E91: Wireless Mouse | F91: Peripherals | G91: 37 | H91: 31.46 | I91: =G91*H91 -> 1164.02 | J91: =I91*0.519 -> 604.12638 | K91: =I91-J91 -> 559.89362 | L91: =IF(I91=0,0,K91/I91) -> 0.481
A92: 45327 | B92: Feb | C92: North | D92: Grace Akinyi | E92: Webcam HD | F92: Accessories | G92: 1 | H92: 142.53 | I92: =G92*H92 -> 142.53 | J92: =I92*0.614 -> 87.51342 | K92: =I92-J92 -> 55.01658 | L92: =IF(I92=0,0,K92/I92) -> 0.386
A93: 45477 | B93: Jul | C93: Central | D93: Eve Wanjiku | E93: Ergonomic Chair | F93: Furniture | G93: 46 | H93: 402.26 | I93: =G93*H93 -> 18503.96 | J93: =I93*0.485 -> 8974.4206 | K93: =I93-J93 -> 9529.5394 | L93: =IF(I93=0,0,K93/I93) -> 0.515
A94: 45607 | B94: Nov | C94: East | D94: Frank Otieno | E94: Ergonomic Chair | F94: Furniture | G94: 30 | H94: 440.32 | I94: =G94*H94 -> 13209.6 | J94: =I94*0.596 -> 7872.9216 | K94: =I94-J94 -> 5336.6784 | L94: =IF(I94=0,0,K94/I94) -> 0.404
A95: 45417 | B95: May | C95: West | D95: Grace Akinyi | E95: Wireless Mouse | F95: Peripherals | G95: 18 | H95: 32.32 | I95: =G95*H95 -> 581.76 | J95: =I95*0.499 -> 290.29824 | K95: =I95-J95 -> 291.46176 | L95: =IF(I95=0,0,K95/I95) -> 0.501
A96: 45464 | B96: Jun | C96: South | D96: Frank Otieno | E96: Laptop Pro | F96: Computers | G96: 32 | H96: 1435.77 | I96: =G96*H96 -> 45944.64 | J96: =I96*0.486 -> 22329.095 | K96: =I96-J96 -> 23615.545 | L96: =IF(I96=0,0,K96/I96) -> 0.514
A97: 45424 | B97: May | C97: East | D97: Alice Mwangi | E97: Webcam HD | F97: Accessories | G97: 18 | H97: 143.72 | I97: =G97*H97 -> 2586.96 | J97: =I97*0.59 -> 1526.3064 | K97: =I97-J97 -> 1060.6536 | L97: =IF(I97=0,0,K97/I97) -> 0.41
A98: 45556 | B98: Sep | C98: Central | D98: David Kamau | E98: Mechanical Keyboard | F98: Peripherals | G98: 6 | H98: 82.09 | I98: =G98*H98 -> 492.54 | J98: =I98*0.531 -> 261.53874 | K98: =I98-J98 -> 231.00126 | L98: =IF(I98=0,0,K98/I98) -> 0.469
A99: 45645 | B99: Dec | C99: North | D99: Bob Ochieng | E99: Ergonomic Chair | F99: Furniture | G99: 42 | H99: 477.54 | I99: =G99*H99 -> 20056.68 | J99: =I99*0.54 -> 10830.607 | K99: =I99-J99 -> 9226.0728 | L99: =IF(I99=0,0,K99/I99) -> 0.46
A100: 45442 | B100: May | C100: Central | D100: Frank Otieno | E100: Mechanical Keyboard | F100: Peripherals | G100: 26 | H100: 94.12 | I100: =G100*H100 -> 2447.12 | J100: =I100*0.511 -> 1250.4783 | K100: =I100-J100 -> 1196.6417 | L100: =IF(I100=0,0,K100/I100) -> 0.489
...

Sheet Employee Data
A1: Employee ID | B1: Name | C1: Department | D1: Role | E1: Hire Date | F1: Salary (KES) | G1: Years Exp | H1: Performance | I1: Satisfaction | J1: Remote %
A2: EMP1000 | B2: Amara Osei | C2: HR | D2: Coordinator | E2: 42903 | F2: 1425396 | G2: 2 | H2: 5 | I2: 4.6 | J2: 20
A3: EMP1001 | B3: Brice Mutua | C3: Design | D3: Designer | E3: 44093 | F3: 1880484 | G3: 8 | H3: 4.5 | I3: 4.1 | J3: 80
A4: EMP1002 | B4: Cleo Nzioka | C4: Marketing | D4: Analyst | E4: 43669 | F4: 2981364 | G4: 8 | H4: 3.8 | I4: 4.5 | J4: 80
A5: EMP1003 | B5: Diana Weru | C5: Marketing | D5: Analyst | E5: 44138 | F5: 2135496 | G5: 8 | H5: 4.2 | I5: 3.7 | J5: 80
A6: EMP1004 | B6: Elias Korir | C6: Sales | D6: Rep | E6: 44467 | F6: 894312 | G6: 14 | H6: 2.8 | I6: 3.3 | J6: 20
A7: EMP1005 | B7: Fatuma Hassan | C7: Sales | D7: Senior Rep | E7: 43268 | F7: 1613532 | G7: 14 | H7: 2.7 | I7: 3.4 | J7: 80
A8: EMP1006 | B8: George Maina | C8: HR | D8: Coordinator | E8: 43756 | F8: 1013892 | G8: 9 | H8: 4.1 | I8: 4.2 | J8: 80
A9: EMP1007 | B9: Hilda Chebet | C9: Sales | D9: Rep | E9: 44106 | F9: 809244 | G9: 2 | H9: 2.6 | I9: 4.3 | J9: 80
A10: EMP1008 | B10: Ivan Omondi | C10: HR | D10: Director | E10: 43387 | F10: 2664396 | G10: 11 | H10: 2.6 | I10: 4.8 | J10: 80
A11: EMP1009 | B11: Jane Gitonga | C11: HR | D11: Director | E11: 43685 | F11: 2874792 | G11: 7 | H11: 3.2 | I11: 3.1 | J11: 0
A12: EMP1010 | B12: Kevin Njoroge | C12: Sales | D12: Senior Rep | E12: 44423 | F12: 1361796 | G12: 6 | H12: 4 | I12: 3.6 | J12: 100
A13: EMP1011 | B13: Lydia Waweru | C13: Operations | D13: Director | E13: 44017 | F13: 1885608 | G13: 9 | H13: 3.9 | I13: 3.6 | J13: 50
... A31: EMP1029 | B31: Dora Musyoka | C31: HR | D31: Director | E31: 43457 | F31: 2258268 | G31: 6 | H31: 3.7 | I31: 4.1 | J31: 100

Sheet Summary Dashboard
A1: 📊 DATAFORGE SAMPLE DATASET
A2: Auto-generated sample dataset for testing the DataForge AI Analysis Platform
A4: SALES SUMMARY
A5: Total Transactions | B5: ='Sales Data'!G252 -> 6387 | C5: Total Units Sold | D5: ='Sales Data'!G252 -> 6387
A6: Total Revenue (KES) | B6: =ROUND('Sales Data'!I252,2) -> 2265793.4 | C6: Total COGS (KES) | D6: =ROUND('Sales Data'!J252,2) -> 1219175.9
A7: Total Gross Profit | B7: =ROUND('Sales Data'!K252,2) -> 1046617.5 | C7: Overall Margin | D7: ='Sales Data'!L252 -> 0.46192096
A9: EMPLOYEE SUMMARY
A10: Total Employees | B10: =COUNTA('Employee Data'!A2:A31) -> 30 | C10: Avg Salary (KES) | D10: =AVERAGE('Employee Data'!F2:F31) -> 1916802
A11: Avg Performance | B11: =AVERAGE('Employee Data'!H2:H31) -> 3.5733333 | C11: Avg Satisfaction | D11: =AVERAGE('Employee Data'!I2:I31) -> 4.11
A12: Avg Years Exp | B12: =AVERAGE('Employee Data'!G2:G31) -> 8.1333333 | C12: Avg Remote % | D12: =AVERAGE('Employee Data'!J2:J31) -> 59.666667
A14: 📌 Suggested Analyses
A15: → Show monthly revenue trend and identify best performing month
A16: → Compare gross margin % across product categories
A17: → Analyze salary distribution by department
A18: → Find correlation between experience and performance rating
A19: → Identify top 5 sales reps by total revenue
A20: → Show regional sales breakdown with a pie chart
